{"cameraMode":{"drawMode":0,"name":"Shaded","section":"Shading Mode"},"sceneLighting":true,"audioPlay":false,"sceneViewState":{"m_AlwaysRefresh":false,"showFog":true,"showSkybox":true,"showFlares":true,"showImageEffects":true,"showParticleSystems":true,"showVisualEffectGraphs":true,"m_FxEnabled":true},"in2DMode":false,"pivot":{"x":-0.24328723549842835,"y":0.1060245931148529,"z":0.21377545595169068},"rotation":{"x":-0.02730356715619564,"y":-0.01439680065959692,"z":0.00039292496512643993,"w":-0.9995246529579163},"size":1.7687510251998902,"orthographic":false}